triagent/__init__.py
triagent/__main__.py
triagent/_version.py
triagent/api.py
triagent/auth.py
triagent/cli.py
triagent/config.py
triagent/hooks.py
triagent/permissions.py
triagent/py.typed
triagent/sdk_client.py
triagent/session_logger.py
triagent/versions.py
triagent/commands/__init__.py
triagent/commands/clear.py
triagent/commands/config.py
triagent/commands/confirm.py
triagent/commands/exit.py
triagent/commands/help.py
triagent/commands/init.py
triagent/commands/persona.py
triagent/commands/registry.py
triagent/commands/team.py
triagent/commands/versions.py
triagent/mcp/__init__.py
triagent/mcp/setup.py
triagent/mcp/tools.py
triagent/sandbox/__init__.py
triagent/sandbox/events.py
triagent/sandbox/runner.py
triagent/sandbox/session_store.py
triagent/security/__init__.py
triagent/security/azure_auth.py
triagent/security/constants.py
triagent/security/corporate_detect.py
triagent/security/crypto.py
triagent/security/exceptions.py
triagent/security/group_membership.py
triagent/skills/__init__.py
triagent/skills/encrypted_loader.py
triagent/skills/loader.py
triagent/skills/models.py
triagent/skills/skill_loader.py
triagent/skills/system.py
triagent/skills/template_loader.py
triagent/skills/encrypted/.gitkeep
triagent/startup/__init__.py
triagent/startup/welcome.py
triagent/teams/__init__.py
triagent/teams/config.py
triagent/tools/__init__.py
triagent/tools/azure_cli.py
triagent/tools/error_recovery.py
triagent/ui/__init__.py
triagent/ui/banner.py
triagent/ui/command_picker.py
triagent/ui/indicators.py
triagent/ui/prompt.py
triagent/ui/theme.py
triagent/utils/__init__.py
triagent/utils/environment.py
triagent/utils/windows.py
triagent/visibility/__init__.py
triagent/visibility/subagent_visibility.py
triagent/web/__init__.py
triagent/web/config.py
triagent/web/local_sessions_api.py
triagent/web/sessions_server.py
triagent/web/container/__init__.py
triagent/web/container/chainlit_app.py
triagent/web/container/session_manager.py
triagent/web/services/__init__.py
triagent-1.4.0.dist-info/METADATA
triagent-1.4.0.dist-info/WHEEL
triagent-1.4.0.dist-info/entry_points.txt
triagent-1.4.0.dist-info/licenses/LICENSE
triagent-1.4.0.dist-info/RECORD
