Metadata-Version: 2.4
Name: triagent
Version: 1.4.0
Summary: Claude-powered CLI for Azure DevOps automation
Project-URL: Homepage, https://github.com/sdandey/triagent
Project-URL: Repository, https://github.com/sdandey/triagent
Project-URL: Issues, https://github.com/sdandey/triagent/issues
Author-email: Santosh Dandey <sdandey@deloitte.com>
License: MIT
License-File: LICENSE
Keywords: agent,ai,automation,azure-devops,claude,cli
Classifier: Development Status :: 3 - Alpha
Classifier: Environment :: Console
Classifier: Intended Audience :: Developers
Classifier: License :: OSI Approved :: MIT License
Classifier: Operating System :: OS Independent
Classifier: Programming Language :: Python :: 3
Classifier: Programming Language :: Python :: 3.11
Classifier: Programming Language :: Python :: 3.12
Classifier: Topic :: Software Development :: Libraries :: Python Modules
Requires-Python: >=3.11
Requires-Dist: anthropic>=0.40.0
Requires-Dist: azure-identity>=1.15.0
Requires-Dist: claude-agent-sdk==0.1.21
Requires-Dist: cryptography>=41.0.0
Requires-Dist: httpx>=0.27.0
Requires-Dist: keyring>=25.0.0
Requires-Dist: prompt-toolkit>=3.0.0
Requires-Dist: python-dotenv>=1.0.0
Requires-Dist: pyyaml>=6.0
Requires-Dist: readchar>=4.2.0
Requires-Dist: rich>=13.0.0
Requires-Dist: typer>=0.12.0
Provides-Extra: dev
Requires-Dist: mypy>=1.10.0; extra == 'dev'
Requires-Dist: pytest-asyncio>=0.23.0; extra == 'dev'
Requires-Dist: pytest-cov>=5.0.0; extra == 'dev'
Requires-Dist: pytest-timeout>=2.3.0; extra == 'dev'
Requires-Dist: pytest>=8.0.0; extra == 'dev'
Requires-Dist: python-semantic-release>=9.0.0; extra == 'dev'
Requires-Dist: ruff>=0.4.0; extra == 'dev'
Provides-Extra: web
Requires-Dist: azure-identity>=1.15.0; extra == 'web'
Requires-Dist: chainlit>=1.0.0; extra == 'web'
Requires-Dist: fastapi>=0.110.0; extra == 'web'
Requires-Dist: msal>=1.26.0; extra == 'web'
Requires-Dist: nest-asyncio>=1.5.0; extra == 'web'
Requires-Dist: uvicorn>=0.27.0; extra == 'web'
